SDPA_WV_FILES/__init__.py
SDPA_WV_FILES/wv_files.py
SDPA_WV_FILES-0.1.1.dist-info/METADATA
SDPA_WV_FILES-0.1.1.dist-info/WHEEL
SDPA_WV_FILES-0.1.1.dist-info/top_level.txt
SDPA_WV_FILES-0.1.1.dist-info/RECORD
